asdeep/__init__.py
asdeep/database.py
asdeep/dataset.py
asdeep/main.py
asdeep/predict.py
asdeep/train.py
asdeep/zutils.py
asdeep-0.1.3.data/data/data/test.bed.gz
asdeep-0.1.3.data/data/data/test.fa.gz
asdeep-0.1.3.data/data/data/test.gtf.gz
asdeep-0.1.3.data/data/data/test.vcf.gz
asdeep-0.1.3.dist-info/LICENSE
asdeep-0.1.3.dist-info/METADATA
asdeep-0.1.3.dist-info/WHEEL
asdeep-0.1.3.dist-info/entry_points.txt
asdeep-0.1.3.dist-info/top_level.txt
asdeep-0.1.3.dist-info/RECORD
