Metadata-Version: 2.1
Name: asdeep
Version: 0.1.3
Summary: A deep-learning tool to interpret variant function by allelic imbalance.
Home-page: http://pypi.python.org/pypi/asdeep
Author: Zhenhua Zhang
Author-email: zhenhua.zhang217@gmail.com
Maintainer: Zhenhua Zhang
Maintainer-email: zhenhua.zhang217@gmail.com
License: MIT
Project-URL: Bug Tracker, https://github.com/zhenhua-zhang/asdeep/issue
Keywords: Deep learning,allele-specific analysis,functional interpration
Platform: any
Classifier: Programming Language :: Python :: 3
Classifier: License :: OSI Approved :: MIT License
Classifier: Operating System :: OS Independent
Classifier: Topic :: Scientific/Engineering :: Bio-Informatics
Requires-Python: >=3.7
License-File: LICENSE
Requires-Dist: pysam
Requires-Dist: numpy
Requires-Dist: scipy
Requires-Dist: matplotlib
Requires-Dist: scikit-learn
Requires-Dist: torch
Requires-Dist: torchvision
Requires-Dist: tensorboard
Requires-Dist: numpy-hilbert-curve
